{
    "self": {
        "respondentUserId": "user_682a07e41a8ee0.40597578",
        "respondentUsername": "aya1a9a.v",
        "answers": {
            "q_memory": 4,
            "q_decision_speed": 2,
            "q_decision_quality": 7,
            "q_logic_iq": 7,
            "q_attention": 2,
            "q_learning_ability": 5,
            "q_intuition": 7,
            "q_creativity": 7,
            "q_causality": 7,
            "q_critical_thinking": 5,
            "q_fantasy": 7,
            "q_intro_extro": 4,
            "q_empathy": 4,
            "q_conflict_proneness": 4,
            "q_trust": 4,
            "q_inclusivity": 4,
            "q_teamwork": 6,
            "q_leading": 4,
            "q_feedbacking": 7,
            "q_assertiveness": 7,
            "q_perfectionism": 6,
            "q_team_influence": 5,
            "q_responsibility": 7,
            "q_problem_solving": 6,
            "q_work_engagement": 7,
            "q_punctuality": 7,
            "q_age_appearance": 2,
            "q_wellness": 1,
            "q_politics": 4,
            "q_happiness": 2,
            "fin_literacy": 1,
            "q_esoteric": 5,
            "q_religiosity": 1,
            "q_endurance": 2,
            "q_sense_of_humor": 7,
            "q_emotional_control": 2,
            "q_guilt": 7,
            "q_optimism": 3,
            "q_stress_resistance": 3,
            "q_adaptability": 5,
            "q_self_esteem": 4,
            "q_self_reflection": 7,
            "q_uncertainty_tolerance": 2,
            "q_victim": 6,
            "q_rescuer": 7,
            "q_persecutor": 5,
            "q_nonconforming": 5,
            "q_modesty": 5,
            "q_apathy": 2,
            "q_sarcastic": 7,
            "q_offensiveness": 6,
            "q_decisiveness": 3,
            "q_reservedness": 7,
            "q_conservatism": 1,
            "q_risk_taking": 5,
            "q_pleasure_seeking": 5,
            "q_commercialism": 5,
            "q_inactivity_preference": 7,
            "q_pride": 7,
            "q_social_comparison": 7,
            "q_hobby": 5,
            "q_interest_movies": 5,
            "q_interest_games": 4,
            "q_interest_books": 5,
            "q_interest_anime": 4,
            "q_interest_drawing": 5,
            "q_interest_music": 5,
            "q_interest_sports": 1,
            "q_interest_science_tech": 1
        },
        "timestamp": "2025-05-18T18:26:05+02:00"
    },
    "others": []
}